Workbook
Name Slicer_Category: #N/A
Name Slicer_Months__Order_Date: #N/A
Name Slicer_Payment_Mode: #N/A
Name Slicer_Region: #N/A
Name Slicer_State: #N/A

Sheet README
C3: FLIPKART SALES DASHBOARD PROJECT
C5: Project Description
C6: This project is based on Flipkart's sales dataset. Using Microsoft
C7: Excel, we performed data cleaning, calculations, and created an
C8: interactive dashboard to analyze sales, profit, customers, and other key
C9: metrics.
C11: Objectives
C12: - Calculate Total Sales, Profit, Orders, and Customers
C13: - Analyze Region-wise & State-wise performance
C14: - Category-wise and Top Products analysis
C15: - Understand Payment mode usage
C16: - Monthly/Yearly growth tracking
... C42: Use filters (slicers) to view interactive analysis

Sheet Raw Data
A1: Order_ID | B1: Customer_ID | C1: Product | D1: Category | E1: Order_Date | F1: Ship_Date | G1: State | H1: Region | I1: Quantity | J1: Price | K1: Discount(%) | L1: Order_Value | M1: Profit | N1: Payment_Mode
A2: ORD1001 | B2: CUST101 | C2: Mobile | D2: Electronics | E2: 45296 | F2: 45298 | G2: Andhra Pradesh | H2: North | I2: 2 | J2: 15000 | K2: 10 | L2: 27000 | M2: 3500 | N2: UPI
A3: ORD1002 | B3: CUST102 | C3: Laptop | D3: Electronics | E3: 45332 | F3: 45336 | G3: Arunachal Pradesh | H3: South | I3: 1 | J3: 50000 | K3: 5 | L3: 47500 | M3: 6000 | N3: Credit Card
A4: ORD1003 | B4: CUST103 | C4: Shoes | D4: Fashion | E4: 45354 | F4: 45356 | G4: Assam | H4: West | I4: 3 | J4: 2000 | K4: 0 | L4: 6000 | M4: 800 | N4: COD
A5: ORD1004 | B5: CUST104 | C5: Watch | D5: Fashion | E5: 45371 | F5: 45373 | G5: Bihar | H5: East | I5: 1 | J5: 2500 | K5: 20 | L5: 2000 | M5: 300 | N5: Wallet
A6: ORD1005 | B6: CUST105 | C6: TV | D6: Electronics | E6: 45383 | F6: 45388 | G6: Jammu Kashmir | H6: North | I6: 1 | J6: 40000 | K6: 15 | L6: 34000 | M6: 4500 | N6: Debit Card
A7: ORD1006 | B7: CUST106 | C7: Microwave | D7: Home Appliance | E7: 45390 | F7: 45394 | G7: Gujarat | H7: South | I7: 2 | J7: 8000 | K7: 0 | L7: 16000 | M7: 2500 | N7: UPI
A8: ORD1007 | B8: CUST107 | C8: Camera | D8: Electronics | E8: 45397 | F8: 45400 | G8: Haryana | H8: West | I8: 1 | J8: 25000 | K8: 10 | L8: 22500 | M8: 4000 | N8: Credit Card
A9: ORD1008 | B9: CUST108 | C9: Refrigerator | D9: Home Appliance | E9: 45413 | F9: 45416 | G9: Himachal Pradesh | H9: East | I9: 1 | J9: 30000 | K9: 5 | L9: 28500 | M9: 3500 | N9: COD
A10: ORD1009 | B10: CUST109 | C10: AC | D10: Home Appliance | E10: 45422 | F10: 45427 | G10: Jharkhand | H10: North | I10: 1 | J10: 35000 | K10: 0 | L10: 35000 | M10: 5000 | N10: UPI
A11: ORD1010 | B11: CUST110 | C11: Headphones | D11: Electronics | E11: 45432 | F11: 45435 | G11: Karnataka | H11: South | I11: 4 | J11: 2000 | K11: 20 | L11: 6400 | M11: 1200 | N11: Wallet
A12: ORD1011 | B12: CUST111 | C12: Mobile | D12: Electronics | E12: 45296 | F12: 45298 | G12: Kerala | H12: North | I12: 2 | J12: 15000 | K12: 10 | L12: 27000 | M12: 3500 | N12: UPI
A13: ORD1012 | B13: CUST112 | C13: Laptop | D13: Electronics | E13: 45332 | F13: 45336 | G13: Ladakh | H13: South | I13: 1 | J13: 50000 | K13: 5 | L13: 47500 | M13: 6000 | N13: Credit Card
... A101: ORD1100 | B101: CUST200 | C101: Refrigerator | D101: Home Appliance | E101: 45413 | F101: 45416 | G101: Ladakh | H101: East | I101: 1 | J101: 30000 | K101: 5 | L101: 28500 | M101: 3500 | N101: COD

Sheet Calulation
C5: Sales Performance | F5: Region wise Sales | I5: Region wise Profit | L5: Payment mode wise customer
C7: Total Sales | D7: =SUM('Raw Data'!L2:L101) -> 2307500 | F7: Region | G7: Sales | I7: Region | J7: Profit | L7: Payment Mode | M7: Customers
C8: Total Profit | D8: =SUM('Raw Data'!M2:M101) -> 316200 | F8: {=_xlfn.UNIQUE('Raw Data'!H2:H101)} -> North | G8: =SUMIF('Raw Data'!$H$2:$H$101,F8,'Raw Data'!$L$2:$L$101) -> 978000 | I8: {=_xlfn.UNIQUE('Raw Data'!H2:H101)} -> North | J8: =SUMIF('Raw Data'!$H$2:$H$101,F8,'Raw Data'!$M$2:$M$101) -> 131500 | L8: {=_xlfn.UNIQUE('Raw Data'!N2:N101)} -> UPI | M8: {=COUNTA(_xlfn.UNIQUE(_xlfn._xlws.FILTER('Raw Data'!B$2:B$101, 'Raw Data'!N$2:N$101=L8)))} -> 29
F9: South | G9: =SUMIF('Raw Data'!$H$2:$H$101,F9,'Raw Data'!$L$2:$L$101) -> 746000 | I9: South | J9: =SUMIF('Raw Data'!$H$2:$H$101,F9,'Raw Data'!$M$2:$M$101) -> 100500 | L9: Credit Card | M9: {=COUNTA(_xlfn.UNIQUE(_xlfn._xlws.FILTER('Raw Data'!B$2:B$101, 'Raw Data'!N$2:N$101=L9)))} -> 21
C10: Avgerage Order Value | D10: =AVERAGE('Raw Data'!L2:L101) -> 23075 | F10: West | G10: =SUMIF('Raw Data'!$H$2:$H$101,F10,'Raw Data'!$L$2:$L$101) -> 274500 | I10: West | J10: =SUMIF('Raw Data'!$H$2:$H$101,F10,'Raw Data'!$M$2:$M$101) -> 45600 | L10: COD | M10: {=COUNTA(_xlfn.UNIQUE(_xlfn._xlws.FILTER('Raw Data'!B$2:B$101, 'Raw Data'!N$2:N$101=L10)))} -> 22
C11: Total Quantity Sold | D11: =SUM('Raw Data'!I2:I101) -> 160 | F11: East | G11: =SUMIF('Raw Data'!$H$2:$H$101,F11,'Raw Data'!$L$2:$L$101) -> 309000 | I11: East | J11: =SUMIF('Raw Data'!$H$2:$H$101,F11,'Raw Data'!$M$2:$M$101) -> 38600 | L11: Wallet | M11: {=COUNTA(_xlfn.UNIQUE(_xlfn._xlws.FILTER('Raw Data'!B$2:B$101, 'Raw Data'!N$2:N$101=L11)))} -> 17
L12: Debit Card | M12: {=COUNTA(_xlfn.UNIQUE(_xlfn._xlws.FILTER('Raw Data'!B$2:B$101, 'Raw Data'!N$2:N$101=L12)))} -> 11
F14: Category wise sales | I14: Product wise Profitability | L14: Product wise Quantity
F16: Category | G16: Sales | I16: Product | J16: Profit | L16: Product | M16: Quantity
F17: {=_xlfn.UNIQUE('Raw Data'!D2:D101)} -> Electronics | G17: =SUMIF('Raw Data'!$D$2:$D$101,F17,'Raw Data'!$L$2:$L$101) -> 1502500 | I17: {=_xlfn.UNIQUE('Raw Data'!C2:C101)} -> Mobile | J17: =SUMIF('Raw Data'!$C$2:$C$101,I17,'Raw Data'!$M$2:$M$101) -> 42000 | L17: {=_xlfn.UNIQUE('Raw Data'!C2:C101)} -> Mobile | M17: =SUMIF('Raw Data'!$C$2:$C$101, L17, 'Raw Data'!$I$2:$I$101) -> 24
F18: Fashion | G18: =SUMIF('Raw Data'!$D$2:$D$101,F18,'Raw Data'!$L$2:$L$101) -> 96000 | I18: Laptop | J18: =SUMIF('Raw Data'!$C$2:$C$101,I18,'Raw Data'!$M$2:$M$101) -> 72000 | L18: Laptop | M18: =SUMIF('Raw Data'!$C$2:$C$101, L18, 'Raw Data'!$I$2:$I$101) -> 12
F19: Home Appliance | G19: =SUMIF('Raw Data'!$D$2:$D$101,F19,'Raw Data'!$L$2:$L$101) -> 709000 | I19: Shoes | J19: =SUMIF('Raw Data'!$C$2:$C$101,I19,'Raw Data'!$M$2:$M$101) -> 9600 | L19: Shoes | M19: =SUMIF('Raw Data'!$C$2:$C$101, L19, 'Raw Data'!$I$2:$I$101) -> 36
I20: Watch | J20: =SUMIF('Raw Data'!$C$2:$C$101,I20,'Raw Data'!$M$2:$M$101) -> 3600 | L20: Watch | M20: =SUMIF('Raw Data'!$C$2:$C$101, L20, 'Raw Data'!$I$2:$I$101) -> 12
F21: Category wise Quantity | I21: TV | J21: =SUMIF('Raw Data'!$C$2:$C$101,I21,'Raw Data'!$M$2:$M$101) -> 49500 | L21: TV | M21: =SUMIF('Raw Data'!$C$2:$C$101, L21, 'Raw Data'!$I$2:$I$101) -> 11
I22: Microwave | J22: =SUMIF('Raw Data'!$C$2:$C$101,I22,'Raw Data'!$M$2:$M$101) -> 22500 | L22: Microwave | M22: =SUMIF('Raw Data'!$C$2:$C$101, L22, 'Raw Data'!$I$2:$I$101) -> 18
F23: Category | G23: Quantity | I23: Camera | J23: =SUMIF('Raw Data'!$C$2:$C$101,I23,'Raw Data'!$M$2:$M$101) -> 36000 | L23: Camera | M23: =SUMIF('Raw Data'!$C$2:$C$101, L23, 'Raw Data'!$I$2:$I$101) -> 9
F24: {=_xlfn.UNIQUE('Raw Data'!D2:D101)} -> Electronics | G24: =SUMIF('Raw Data'!$D$2:$D$101, F24, 'Raw Data'!$I$2:$I$101) -> 76 | I24: Refrigerator | J24: =SUMIF('Raw Data'!$C$2:$C$101,I24,'Raw Data'!$M$2:$M$101) -> 35000 | L24: Refrigerator | M24: =SUMIF('Raw Data'!$C$2:$C$101, L24, 'Raw Data'!$I$2:$I$101) -> 10
F25: Fashion | G25: =SUMIF('Raw Data'!$D$2:$D$101, F25, 'Raw Data'!$I$2:$I$101) -> 48 | I25: AC | J25: =SUMIF('Raw Data'!$C$2:$C$101,I25,'Raw Data'!$M$2:$M$101) -> 40000 | L25: AC | M25: =SUMIF('Raw Data'!$C$2:$C$101, L25, 'Raw Data'!$I$2:$I$101) -> 8
F26: Home Appliance | G26: =SUMIF('Raw Data'!$D$2:$D$101, F26, 'Raw Data'!$I$2:$I$101) -> 36 | I26: Headphones | J26: =SUMIF('Raw Data'!$C$2:$C$101,I26,'Raw Data'!$M$2:$M$101) -> 6000 | L26: Headphones | M26: =SUMIF('Raw Data'!$C$2:$C$101, L26, 'Raw Data'!$I$2:$I$101) -> 20

Sheet Combo Chart
J3: Row Labels | K3: Sum of Order_Value | L3: Sum of Profit
J4: Jan | K4: 324000 | L4: 42000
J5: Apr | K5: 374000 | L5: 49500
J6: May | K6: 280000 | L6: 40000
J7: Grand Total | K7: 978000 | L7: 131500

Sheet Waterfall Chart
H5: Row Labels | I5: Sum of Profit | K5: Category | L5: Profit
H6: Electronics | I6: 91500 | K6: =H6 -> Electronics | L6: =GETPIVOTDATA("Profit",$H$5,"Category",K6) -> 91500
H7: Home Appliance | I7: 40000 | K7: =H7 -> Home Appliance | L7: =GETPIVOTDATA("Profit",$H$5,"Category",K7) -> 40000
H8: Grand Total | I8: 131500 | K8: =H8 -> Grand Total | L8: =GETPIVOTDATA("Profit",$H$5,"Category",K8) -> #REF!
K9: =H9 -> 0 | L9: =GETPIVOTDATA("Profit",$H$5) -> 131500

Sheet Pie Chart
I6: Row Labels | J6: Sum of Order_Value
I7: Electronics | J7: 0.71370143
I8: Home Appliance | J8: 0.28629857
I9: Grand Total | J9: 1

Sheet Top 5
I5: Row Labels | J5: Sum of Order_Value
I6: AC | J6: 280000
I7: Mobile | J7: 324000
I8: TV | J8: 374000
I9: Grand Total | J9: 978000

Sheet Map Chart
D9: Row Labels | E9: Sum of Order_Value | G9: State | H9: Sales
D10: Maharashtra | E10: 150900 | G10: =D10 -> Maharashtra | H10: =GETPIVOTDATA("Order_Value",$D$9,"State",G10) -> 150900
D11: Grand Total | E11: 150900 | G11: =D11 -> Grand Total | H11: =GETPIVOTDATA("Order_Value",$D$9,"State",G11) -> #REF!
G12: =D12 -> 0 | H12: =GETPIVOTDATA("Order_Value",$D$9,"State",G12) -> #REF!
G13: =D13 -> 0 | H13: =GETPIVOTDATA("Order_Value",$D$9,"State",G13) -> #REF!
G14: =D14 -> 0 | H14: =GETPIVOTDATA("Order_Value",$D$9,"State",G14) -> #REF!
G15: =D15 -> 0 | H15: =GETPIVOTDATA("Order_Value",$D$9,"State",G15) -> #REF!
G16: =D16 -> 0 | H16: =GETPIVOTDATA("Order_Value",$D$9,"State",G16) -> #REF!
G17: =D17 -> 0 | H17: =GETPIVOTDATA("Order_Value",$D$9,"State",G17) -> #REF!
G18: =D18 -> 0 | H18: =GETPIVOTDATA("Order_Value",$D$9,"State",G18) -> #REF!
G19: =D19 -> 0 | H19: =GETPIVOTDATA("Order_Value",$D$9,"State",G19) -> #REF!
G20: =D20 -> 0 | H20: =GETPIVOTDATA("Order_Value",$D$9,"State",G20) -> #REF!
G21: =D21 -> 0 | H21: =GETPIVOTDATA("Order_Value",$D$9,"State",G21) -> #REF!
G22: =D22 -> 0 | H22: =GETPIVOTDATA("Order_Value",$D$9,"State",G22) -> #REF!
G23: =D23 -> 0 | H23: =GETPIVOTDATA("Order_Value",$D$9,"State",G23) -> #REF!
... G38: =D38 -> 0 | H38: =GETPIVOTDATA("Order_Value",$D$9,"State",G38) -> #REF!

Sheet KPI
C7: Row Labels | D7: Sum of Order_Value | F7: Row Labels | G7: Sum of Profit | J7: Row Labels | K7: Sum of Quantity | M7: Row Labels | N7: Count of Customer_ID
C8: Jan | D8: 324000 | F8: Jan | G8: 42000 | J8: Jan | K8: 24 | M8: Jan | N8: 12
C9: Apr | D9: 374000 | F9: Apr | G9: 49500 | J9: Apr | K9: 11 | M9: Apr | N9: 11
C10: May | D10: 280000 | F10: May | G10: 40000 | J10: May | K10: 8 | M10: May | N10: 8
C11: Grand Total | D11: 978000 | F11: Grand Total | G11: 131500 | J11: Grand Total | K11: 43 | M11: Grand Total | N11: 31
D15: =GETPIVOTDATA("Order_Value",$C$7) -> 978000 | G15: =GETPIVOTDATA("Profit",$F$7) -> 131500 | K15: =GETPIVOTDATA("Quantity",$J$7) -> 43 | N15: =GETPIVOTDATA("Customer_ID",$M$7) -> 31

Sheet KPI MOM
E6: Row Labels | F6: Sum of Order_Value | G6: Sum of Profit | H6: Sum of Quantity | I6: Count of Order_ID
E7: Jan | F7: 324000 | G7: 42000 | H7: 24 | I7: 12
E8: Apr | F8: 374000 | G8: 49500 | H8: 11 | I8: 11
E9: May | F9: 280000 | G9: 40000 | H9: 8 | I9: 8
K13: =(GETPIVOTDATA("Sum of Order_Value",$E$6,"Months (Order_Date)",5)/GETPIVOTDATA("Sum of Order_Value",$E$6,"Months (Order_Date)",4))-1 -> -0.2513369 | L13: =(GETPIVOTDATA("Sum of Profit",$E$6,"Months (Order_Date)",5)/GETPIVOTDATA("Sum of Profit",$E$6,"Months (Order_Date)",4))-1 -> -0.19191919 | M13: =(GETPIVOTDATA("Sum of Quantity",$E$6,"Months (Order_Date)",4)/GETPIVOTDATA("Sum of Quantity",$E$6,"Months (Order_Date)",3))-1 -> #REF! | N13: =(GETPIVOTDATA("Count of Order_ID",$E$6,"Months (Order_Date)",5)/GETPIVOTDATA("Count of Order_ID",$E$6,"Months (Order_Date)",4))-1 -> -0.27272727

Sheet  Dashboard 
